{
  "question_id": "3811070f",
  "original": "integrate(x/sqrt(x**2 + 4), x)",
  "variants": [
    {
      "original": "integrate(x/sqrt(x**2 + 4), x)",
      "requested_difficulty": "easier",
      "variant": "integrate(x/sqrt(x**2 + 4), x)",
      "reasoning": "As a calculus professor who loves elegant simplifications, I see that a substitution \\( u = x^2 + 4 \\) would be beneficial. This allows us to simplify the integral neatly.",
      "variant_response": null,
      "verification_passed": true,
      "evaluation": "equivalent",
      "transformations_used": [
        "simplify composite trigonometric functions",
        "reduce the degree of a polynomial",
        "convert a product to a simpler sum"
      ],
      "solution": "sqrt(x**2 + 4)",
      "evaluations": {
        "2.346": 3.0831685831161804,
        "0.579": 2.0819934428089106,
        "8.167": 8.4080997757363
      },
      "timestamp": "2025-02-02T23:09:30.026978Z"
    },
    {
      "original": "integrate(x/sqrt(x**2 + 4), x)",
      "requested_difficulty": "easier",
      "variant": "integrate(x/(x**2 + 4)**(1/2), x)",
      "reasoning": "As a student who prefers working with polynomials, I recognize that by rewriting the integral as \\(\\int \\frac{x}{\\sqrt{x^2 + 4}} dx\\), we can equate it with a more straightforward rational function.",
      "variant_response": null,
      "verification_passed": true,
      "evaluation": "equivalent",
      "transformations_used": [
        "simplify composite trigonometric functions",
        "reduce the degree of a polynomial",
        "convert a product to a simpler sum"
      ],
      "solution": "sqrt(x**2 + 4)",
      "evaluations": {
        "-2.529": 3.2244178403625217,
        "-5.558": 5.906868646427609,
        "8.319": 8.556091145519886
      },
      "timestamp": "2025-02-02T23:09:30.023163Z"
    },
    {
      "original": "integrate(x/sqrt(x**2 + 4), x)",
      "requested_difficulty": "easier",
      "variant": "integrate(x/(sqrt(x**2 + 4)), x)",
      "reasoning": "As a number theorist fascinated by rational coefficients, I prefer expressing the integrand in rational terms. Here, we can find a common denominator that provides a clearer picture.",
      "variant_response": null,
      "verification_passed": true,
      "evaluation": "equivalent",
      "transformations_used": [
        "simplify composite trigonometric functions",
        "reduce the degree of a polynomial",
        "convert a product to a simpler sum"
      ],
      "solution": "sqrt(x**2 + 4)",
      "evaluations": {
        "1.486": 2.491890971695343,
        "-9.805": 10.006913293532785,
        "8.198": 8.438123098357455
      },
      "timestamp": "2025-02-02T23:09:30.026128Z"
    },
    {
      "original": "integrate(x/sqrt(x**2 + 4), x)",
      "requested_difficulty": "easier",
      "variant": "integrate(1/sqrt(1 + (x/2)**2), x)",
      "reasoning": "As a geometry enthusiast, I think about how the integrand can be viewed under a transformation where it represents a certain geometric area, leading to a simpler integral form reflecting those areas.",
      "variant_response": null,
      "verification_passed": true,
      "evaluation": "easier",
      "transformations_used": [
        "simplify composite trigonometric functions",
        "reduce the degree of a polynomial",
        "convert a product to a simpler sum"
      ],
      "solution": "2*asinh(x/2)",
      "evaluations": {
        "-1.304": -1.2258639717473743,
        "5.149": 3.349107479402709,
        "-8.665": -4.344771540912756
      },
      "timestamp": "2025-02-02T23:09:30.023872Z"
    },
    {
      "original": "integrate(x/sqrt(x**2 + 4), x)",
      "requested_difficulty": "easier",
      "variant": "integrate(1/sqrt(1 + 4/x**2), x)",
      "reasoning": "From a creative mathematician's perspective, I find that dropping the square root could simplify my approach. I can divide the numerator and denominator by \\( x \\), transforming the integral to a more straightforward rational function.",
      "variant_response": null,
      "verification_passed": true,
      "evaluation": "easier",
      "transformations_used": [
        "drop a subexpression",
        "replace a complex fraction with a simpler one",
        "simplify the denominator"
      ],
      "solution": "x*sqrt(1 + 4/x**2)",
      "evaluations": {
        "-7.739": -7.992890516537619,
        "-6.027": -6.350453491194733,
        "2.737": 3.3896307942933435
      },
      "timestamp": "2025-02-02T23:11:05.860784Z"
    },
    {
      "original": "integrate(x/sqrt(x**2 + 4), x)",
      "requested_difficulty": "easier",
      "variant": "integrate(x*(4**0.5)*(x**2 + 4)**(-1/2), x)",
      "reasoning": "A theoretical physicist might favor exponential functions. I can express the square root in exponential form, which often helps in integral evaluation through transformation into exponential integrals.",
      "variant_response": null,
      "verification_passed": true,
      "evaluation": "equivalent",
      "transformations_used": [
        "drop a subexpression",
        "replace a complex fraction with a simpler one",
        "simplify the denominator"
      ],
      "solution": "2.0*sqrt(x**2 + 4)",
      "evaluations": {
        "-9.66": 19.72885867055858,
        "-4.207": 9.31629823461708,
        "-2.739": 6.78353055532781
      },
      "timestamp": "2025-02-02T23:11:06.035953Z"
    },
    {
      "original": "integrate(x/sqrt(x**2 + 4), x)",
      "requested_difficulty": "easier",
      "variant": "integrate(2*x/sqrt((x**2 + 4)), x)",
      "reasoning": "A geometry enthusiast would approach this integral through geometric interpretations of the function, focusing on the area it represents. I simplify to consider half-angle and area representation via substitution, focusing on a triangle relationship within the integral.",
      "variant_response": null,
      "verification_passed": true,
      "evaluation": "easier",
      "transformations_used": [
        "drop a subexpression",
        "replace a complex fraction with a simpler one",
        "simplify the denominator"
      ],
      "solution": "2*sqrt(x**2 + 4)",
      "evaluations": {
        "0.057": 4.00162587639426,
        "7.781": 16.068213479130264,
        "5.256": 11.248072083117876
      },
      "timestamp": "2025-02-02T23:11:05.903465Z"
    },
    {
      "original": "integrate(x/sqrt(x**2 + 4), x)",
      "requested_difficulty": "easier",
      "variant": "integrate(x/sqrt((x**2 + 4)*(1)), x)",
      "reasoning": "From a purely analytic perspective, I wish to convert it into a more usable form via algebraic manipulation. Factoring could help separate the variables more cleanly for manageable integration techniques.",
      "variant_response": null,
      "verification_passed": true,
      "evaluation": "equivalent",
      "transformations_used": [
        "drop a subexpression",
        "replace a complex fraction with a simpler one",
        "simplify the denominator"
      ],
      "solution": "sqrt(x**2 + 4)",
      "evaluations": {
        "4.276": 4.720596948595655,
        "-1.262": 2.3650262157997832,
        "0.576": 2.0813865246470566
      },
      "timestamp": "2025-02-02T23:11:06.162090Z"
    },
    {
      "original": "integrate(x/sqrt(x**2 + 4), x)",
      "requested_difficulty": "easier",
      "variant": "integrate(x, x)",
      "reasoning": "A creative mathematician might see that separating the integral into components allows for easier evaluation. I could simplify the base terms, allowing for a dis-integrable form that streamlines computation.",
      "variant_response": null,
      "verification_passed": true,
      "evaluation": "easier",
      "transformations_used": [
        "drop a subexpression",
        "replace a complex fraction with a simpler one",
        "simplify the denominator"
      ],
      "solution": "x**2/2",
      "evaluations": {
        "1.07": 0.5722030423204296,
        "-0.029": 0.00041094571802157467,
        "-7.757": 30.083962416964802
      },
      "timestamp": "2025-02-02T23:11:05.953254Z"
    },
    {
      "original": "integrate(x/sqrt(x**2 + 4), x)",
      "requested_difficulty": "easier",
      "variant": "integrate(2*x/sqrt(x**2 + 4), x)",
      "reasoning": "As theoretical physicists often do, I use symmetry to recognize structures that simplify integration. I might transform the integral by a clever substitution to expose more manageable expressions.",
      "variant_response": null,
      "verification_passed": true,
      "evaluation": "easier",
      "transformations_used": [
        "drop a subexpression",
        "replace a complex fraction with a simpler one",
        "simplify the denominator"
      ],
      "solution": "2*sqrt(x**2 + 4)",
      "evaluations": {
        "7.19": 14.926330128051042,
        "-3.383": 7.860147006850809,
        "-9.729": 19.865771340898053
      },
      "timestamp": "2025-02-02T23:11:06.081298Z"
    },
    {
      "original": "integrate(x/sqrt(x**2 + 4), x)",
      "requested_difficulty": "easier",
      "variant": "integrate(x/(sqrt(4) + x**2/2), x)",
      "reasoning": "An engineer prefers computational approaches. For practical computations, I can evaluate the integral by approximating the integrand using a polynomial expansion around \\(x=0\\).",
      "variant_response": null,
      "verification_passed": true,
      "evaluation": "easier",
      "transformations_used": [
        "remove a complicated term",
        "change a function to an easier one",
        "drop a subexpression"
      ],
      "solution": "log(x**2 + 4)",
      "evaluations": {
        "-8.899": 4.4210657741693655,
        "5.765": 3.6172763131069035,
        "-1.472": 1.819390366650088
      },
      "timestamp": "2025-02-02T23:09:30.640494Z"
    },
    {
      "original": "integrate(x/sqrt(x**2 + 4), x)",
      "requested_difficulty": "easier",
      "variant": "integrate(1/(sqrt(4/x**2 + 1)), x)",
      "reasoning": "A number theorist often looks at rational coefficients. I can break down the integral into a simpler fraction that removes the square root.",
      "variant_response": null,
      "verification_passed": true,
      "evaluation": "easier",
      "transformations_used": [
        "remove a complicated term",
        "change a function to an easier one",
        "drop a subexpression"
      ],
      "solution": "x*sqrt(1 + 4/x**2)",
      "evaluations": {
        "0.105": 2.002737061072165,
        "-8.613": -8.842441063073695,
        "1.121": 2.2926721023392043
      },
      "timestamp": "2025-02-02T23:09:30.642492Z"
    },
    {
      "original": "integrate(x/sqrt(x**2 + 4), x)",
      "requested_difficulty": "easier",
      "variant": "integrate(x/(sqrt(x**2 + 1)), x)",
      "reasoning": "Thinking geometrically, I can interpret this integral in terms of the area under a curve modified by a vertical shift, simplifying my calculations by adjusting the function accordingly.",
      "variant_response": null,
      "verification_passed": true,
      "evaluation": "easier",
      "transformations_used": [
        "remove a complicated term",
        "change a function to an easier one",
        "drop a subexpression"
      ],
      "solution": "sqrt(x**2 + 1)",
      "evaluations": {
        "1.587": 1.8756324488355733,
        "7.952": 8.014585761957294,
        "-1.365": 1.6924688075299308
      },
      "timestamp": "2025-02-02T23:09:30.638663Z"
    },
    {
      "original": "integrate(x/sqrt(x**2 + 4), x)",
      "requested_difficulty": "easier",
      "variant": "integrate(x/sqrt(x**2), x)",
      "reasoning": "The calculus professor also appreciates evaluating limits at infinity. I can consider the asymptotic behavior near \\(x \\to \\infty\\) when the integral becomes simpler.",
      "variant_response": null,
      "verification_passed": true,
      "evaluation": "easier",
      "transformations_used": [
        "remove a complicated term",
        "change a function to an easier one",
        "drop a subexpression"
      ],
      "solution": "x**2/sqrt(x**2)",
      "evaluations": {
        "3.466": 3.4659678850754325,
        "0.901": 0.9009098645378355,
        "-9.069": 9.068996419161579
      },
      "timestamp": "2025-02-02T23:09:30.639658Z"
    },
    {
      "original": "integrate(x/sqrt(x**2 + 4), x)",
      "requested_difficulty": "easier",
      "variant": "integrate(x/sqrt(4), x)",
      "reasoning": "As a student who enjoys rational functions, I can rationalize the denominator, leading to a more straightforward integrand to work with.",
      "variant_response": null,
      "verification_passed": true,
      "evaluation": "easier",
      "transformations_used": [
        "remove a complicated term",
        "change a function to an easier one",
        "drop a subexpression"
      ],
      "solution": "x**2/4",
      "evaluations": {
        "-4.655": 5.417945719334966,
        "2.908": 2.1145279897384186,
        "7.878": 15.516483065454246
      },
      "timestamp": "2025-02-02T23:09:30.715125Z"
    },
    {
      "original": "integrate(x/sqrt(x**2 + 4), x)",
      "requested_difficulty": "easier",
      "variant": "integrate(x/abs(x), x)",
      "reasoning": "A creative mathematician might want to find a simpler approximation. By estimating \\(\\sqrt{x^2 + 4} \\approx |x|\\) for large \\(x\\), the integral simplifies.",
      "variant_response": null,
      "verification_passed": true,
      "evaluation": "easier",
      "transformations_used": [
        "remove a complicated term",
        "change a function to an easier one",
        "drop a subexpression"
      ],
      "solution": null,
      "evaluations": {},
      "timestamp": "2025-02-02T23:09:30.641350Z"
    },
    {
      "original": "integrate(x/sqrt(x**2 + 4), x)",
      "requested_difficulty": "easier",
      "variant": "integrate(x/(2 + x**2/4)**(1/2), x)",
      "reasoning": "As a student focused on polynomials, I want to reduce complexity by rewriting \\(\\sqrt{x^2 + 4}\\) using polynomial long division or avoiding complicating terms.",
      "variant_response": null,
      "verification_passed": true,
      "evaluation": "equivalent",
      "transformations_used": [
        "remove a complicated term",
        "eliminate absolute value terms",
        "drop a subexpression",
        "simplify the denominator",
        "change a function to an easier one"
      ],
      "solution": "2*sqrt(x**2 + 8)",
      "evaluations": {
        "-3.085": 8.3701716297052,
        "-8.033": 17.032010754518165,
        "-6.054": 13.363857350192397
      },
      "timestamp": "2025-02-02T23:11:05.905020Z"
    },
    {
      "original": "integrate(x/sqrt(x**2 + 4), x)",
      "requested_difficulty": "easier",
      "variant": "integrate(2*sin(x)/sqrt(4 - 4*sin(x)**2), x)",
      "reasoning": "The theoretical physicist in me enjoys using trigonometric identities. I might switch to \\(x = 2\\sin(\\theta)\\), which directly relates to the period and amplitude of sine functions.",
      "variant_response": null,
      "verification_passed": true,
      "evaluation": "easier",
      "transformations_used": [
        "remove a complicated term",
        "eliminate absolute value terms",
        "drop a subexpression",
        "simplify the denominator",
        "change a function to an easier one"
      ],
      "solution": null,
      "evaluations": {},
      "timestamp": "2025-02-02T23:11:06.026499Z"
    },
    {
      "original": "integrate(x/sqrt(x**2 + 4), x)",
      "requested_difficulty": "easier",
      "variant": "integrate(1/(sqrt(1 + (x/2)**2)), x)",
      "reasoning": "Emphasis on number theory leads me to focus on rational coefficients. Let\u2019s incorporate rational expressions within the limits to maintain rationality.",
      "variant_response": null,
      "verification_passed": true,
      "evaluation": "easier",
      "transformations_used": [
        "remove a complicated term",
        "eliminate absolute value terms",
        "drop a subexpression",
        "simplify the denominator",
        "change a function to an easier one"
      ],
      "solution": "2*asinh(x/2)",
      "evaluations": {
        "-2.898": -2.33240013386283,
        "-5.808": -3.575446360241899,
        "-3.564": -2.683121264905902
      },
      "timestamp": "2025-02-02T23:11:05.853755Z"
    },
    {
      "original": "integrate(x/sqrt(x**2 + 4), x)",
      "requested_difficulty": "easier",
      "variant": "integrate(x/(x + 2), x)",
      "reasoning": "As the student again but with a refreshed perspective, let\u2019s just replace the square root with a simple linear transformation to reduce complexity.",
      "variant_response": null,
      "verification_passed": true,
      "evaluation": "easier",
      "transformations_used": [
        "remove a complicated term",
        "eliminate absolute value terms",
        "drop a subexpression",
        "simplify the denominator",
        "change a function to an easier one"
      ],
      "solution": "x - 2*log(x + 2)",
      "evaluations": {
        "3.866": 0.3278434875819484,
        "0.137": -1.381812980529084,
        "1.86": -0.8414836255099143
      },
      "timestamp": "2025-02-02T23:11:05.989141Z"
    },
    {
      "original": "integrate(x/sqrt(x**2 + 4), x)",
      "requested_difficulty": "easier",
      "variant": "integrate(1/sqrt(x**2 + 4) + (x * (1/sqrt(x**2 + 4))), x)",
      "reasoning": "As a student fond of polynomials, I can separate the fraction by partial fraction decomposition. This often makes integrals much easier to manage.",
      "variant_response": null,
      "verification_passed": true,
      "evaluation": "equivalent",
      "transformations_used": [
        "eliminate a radical",
        "eliminate absolute value terms",
        "convert a product to a simpler sum"
      ],
      "solution": "sqrt(x**2 + 4) + asinh(x/2)",
      "evaluations": {
        "-3.261": 2.560495792510718,
        "1.088": 2.797453667469457,
        "4.668": 6.662644021309608
      },
      "timestamp": "2025-02-02T23:09:29.251246Z"
    },
    {
      "original": "integrate(x/sqrt(x**2 + 4), x)",
      "requested_difficulty": "easier",
      "variant": "integrate(x * (x**2 + 4)**(-1/2), x)",
      "reasoning": "As a theoretical physicist, I prefer using exponential forms. We can express the radical in the integral using exponentiation to ease integration.",
      "variant_response": null,
      "verification_passed": true,
      "evaluation": "equivalent",
      "transformations_used": [
        "eliminate a radical",
        "eliminate absolute value terms",
        "convert a product to a simpler sum"
      ],
      "solution": "sqrt(x**2 + 4)",
      "evaluations": {
        "7.292": 7.561564802286044,
        "3.62": 4.135503811182677,
        "2.85": 3.4813379882138533
      },
      "timestamp": "2025-02-02T23:09:29.249100Z"
    },
    {
      "original": "integrate(x/sqrt(x**2 + 4), x)",
      "requested_difficulty": "easier",
      "variant": "integrate(x / (2 + x**2/4), x)",
      "reasoning": "As a creative mathematician, I want to find more straightforward functions. If we approximate \\(\\sqrt{x^2 + 4}\\) using a Taylor expansion around \\(x = 0\\), I can get easier integrands.",
      "variant_response": null,
      "verification_passed": true,
      "evaluation": "easier",
      "transformations_used": [
        "drop a subexpression",
        "reduce an exponent",
        "remove nested functions"
      ],
      "solution": "2*log(x**2 + 8)",
      "evaluations": {
        "1.855": 4.874698948076073,
        "-5.503": 7.289771058771955,
        "2.423": 5.259768678623555
      },
      "timestamp": "2025-02-02T23:09:31.087170Z"
    },
    {
      "original": "integrate(x/sqrt(x**2 + 4), x)",
      "requested_difficulty": "easier",
      "variant": "integrate(x / 2, x)",
      "reasoning": "As an engineer, I lean towards rewriting in a form suitable for numerical approximation. For small values of \\(x\\), I can approximate \\(\\sqrt{x^2 + 4} \\approx 2\\).",
      "variant_response": null,
      "verification_passed": true,
      "evaluation": "easier",
      "transformations_used": [
        "drop a subexpression",
        "reduce an exponent",
        "remove nested functions"
      ],
      "solution": "x**2/4",
      "evaluations": {
        "4.515": 5.096181779319265,
        "6.388": 10.200848412496995,
        "5.581": 7.78725603283621
      },
      "timestamp": "2025-02-02T23:09:31.117038Z"
    }
  ],
  "num_valid_variants": 24
}