[
  {
    "original": "integrate(x**2*exp(x), x)",
    "requested_difficulty": "easier",
    "variant": "integrate(x*exp(x), x)",
    "reasoning": "As a calculus professor who loves elegant simplifications, I can reduce the complexity by using integration by parts. Thus, I will change the integrand to a simpler polynomial.",
    "variant_response": null,
    "verification_passed": true,
    "evaluation": "easier",
    "transformations_used": [
      "drop a subexpression",
      "simplify composite trigonometric functions",
      "eliminate a radical"
    ],
    "solution": "(x - 1)*exp(x)",
    "evaluations": {
      "-4.292": -0.07237095146902901,
      "2.365": 14.517880541212481,
      "8.906": 58338.039906435406
    },
    "timestamp": "2025-02-06T23:21:33.762535Z"
  },
  {
    "original": "integrate(x**2*exp(x), x)",
    "requested_difficulty": "easier",
    "variant": "integrate(x**2, x)",
    "reasoning": "As a student who prefers polynomials, I can drop the exponential term and consider just the polynomial part for basic practice. This introduces a simpler integral.",
    "variant_response": null,
    "verification_passed": true,
    "evaluation": "easier",
    "transformations_used": [
      "drop a subexpression",
      "simplify composite trigonometric functions",
      "eliminate a radical"
    ],
    "solution": "x**3/3",
    "evaluations": {
      "-6.65": -98.00617637495075,
      "-6.363": -85.86472211347571,
      "5.925": 69.3244998625553
    },
    "timestamp": "2025-02-06T23:21:32.877106Z"
  },
  {
    "original": "integrate(x**2*exp(x), x)",
    "requested_difficulty": "easier",
    "variant": "integrate(exp(x), x)",
    "reasoning": "From the perspective of a theoretical physicist, I can think of using an exponential function alone by approximating integrands that involve \\( e^x \\). Therefore, I will focus on a different function altogether.",
    "variant_response": null,
    "verification_passed": true,
    "evaluation": "easier",
    "transformations_used": [
      "drop a subexpression",
      "simplify composite trigonometric functions",
      "eliminate a radical"
    ],
    "solution": "exp(x)",
    "evaluations": {
      "5.768": 319.8778794901234,
      "-2.442": 0.08702339088553161,
      "7.23": 1379.7137585233677
    },
    "timestamp": "2025-02-06T23:21:33.973378Z"
  },
  {
    "original": "integrate(x**2*exp(x), x)",
    "requested_difficulty": "easier",
    "variant": "integrate(x**2*(1 + x + x**2 / 2), x)",
    "reasoning": "As an engineer who enjoys practical computations, I can create a simpler numerical integral by assuming \\( x \\) is small and approximating \\( e^x \\) with its series expansion.",
    "variant_response": null,
    "verification_passed": true,
    "evaluation": "easier",
    "transformations_used": [
      "drop a subexpression",
      "simplify composite trigonometric functions",
      "eliminate a radical"
    ],
    "solution": "x**5/10 + x**4/4 + x**3/3",
    "evaluations": {
      "-7.721": -2008.1845204313383,
      "-5.992": -521.8836477674222,
      "5.99": 1164.6122389332038
    },
    "timestamp": "2025-02-06T23:21:33.784481Z"
  },
  {
    "original": "integrate(x**2*exp(x), x)",
    "requested_difficulty": "easier",
    "variant": "integrate(x**2 + 1, x)",
    "reasoning": "As a number theorist fascinated by prime numbers, I can structure my variant to utilize integer coefficients which maintain simplicity while keeping the integral manageable.",
    "variant_response": null,
    "verification_passed": true,
    "evaluation": "easier",
    "transformations_used": [
      "drop a subexpression",
      "simplify composite trigonometric functions",
      "eliminate a radical"
    ],
    "solution": "x**3/3 + x",
    "evaluations": {
      "8.194": 191.5604828628595,
      "8.527": 215.22494663973163,
      "7.638": 156.18482742588242
    },
    "timestamp": "2025-02-06T23:21:35.250422Z"
  },
  {
    "original": "integrate(x**2*exp(x), x)",
    "requested_difficulty": "easier",
    "variant": "integrate(x, x)",
    "reasoning": "From the perspective of a geometry enthusiast, I can visualize the integral geometrically and simplify it to the area under a linear function.",
    "variant_response": null,
    "verification_passed": true,
    "evaluation": "easier",
    "transformations_used": [
      "drop a subexpression",
      "simplify composite trigonometric functions",
      "eliminate a radical"
    ],
    "solution": "x**2/2",
    "evaluations": {
      "5.577": 15.55335009779272,
      "-4.017": 8.069494078827141,
      "-0.871": 0.379361071670497
    },
    "timestamp": "2025-02-06T23:21:33.739794Z"
  },
  {
    "original": "integrate(x**2*exp(x), x)",
    "requested_difficulty": "easier",
    "variant": "integrate(x*exp(x/2), x)",
    "reasoning": "As a calculus professor, I can create an equivalent simpler integrand by halving the power, which reduces the integral's complexity.",
    "variant_response": null,
    "verification_passed": true,
    "evaluation": "easier",
    "transformations_used": [
      "drop a subexpression",
      "simplify composite trigonometric functions",
      "eliminate a radical"
    ],
    "solution": "(2*x - 4)*exp(x/2)",
    "evaluations": {
      "9.666": 1925.72775156645,
      "-9.605": -0.19057212246320676,
      "0.931": -3.405461589652946
    },
    "timestamp": "2025-02-06T23:21:33.932863Z"
  },
  {
    "original": "integrate(x**2*exp(x), x)",
    "requested_difficulty": "easier",
    "variant": "integrate(1, x)",
    "reasoning": "As an engineer focusing on computations, I choose to simplify to just the constant term of \\( e^x \\) as a practical approach to evaluating integrals for small \\( x \\).",
    "variant_response": null,
    "verification_passed": true,
    "evaluation": "easier",
    "transformations_used": [
      "drop a subexpression",
      "simplify composite trigonometric functions",
      "eliminate a radical"
    ],
    "solution": "x",
    "evaluations": {
      "-4.207": -4.207051037788167,
      "8.469": 8.469256105173319,
      "-8.837": -8.836718982277525
    },
    "timestamp": "2025-02-06T23:21:32.892405Z"
  },
  {
    "original": "integrate(x**2*exp(x), x)",
    "requested_difficulty": "easier",
    "variant": "integrate(x**2*(cosh(x) + sinh(x)), x)",
    "reasoning": "From the perspective of a theoretical physicist, I can take advantage of integration techniques involving trigonometric identities. By recognizing that the exponential function can be expressed in sine and cosine form, we can simplify the process.",
    "variant_response": null,
    "verification_passed": true,
    "evaluation": "equivalent",
    "transformations_used": [
      "remove logarithmic terms",
      "eliminate a radical",
      "remove a factor"
    ],
    "solution": "x**2*sinh(x) + x**2*cosh(x) - 2*x*sinh(x) - 2*x*cosh(x) + 2*sinh(x) + 2*cosh(x)",
    "evaluations": {
      "-9.718": 0.006976515548010267,
      "9.735": 1305972.8584039444,
      "-9.495": 0.008363570342908617
    },
    "timestamp": "2025-02-06T23:21:33.739058Z"
  },
  {
    "original": "integrate(x**2*exp(x), x)",
    "requested_difficulty": "easier",
    "variant": "integrate(3, x)",
    "reasoning": "As a fundamental algebraist, simplifying the integrand to a constant helps create a graceful path towards solving the integral as a straight polynomial evaluation.",
    "variant_response": null,
    "verification_passed": true,
    "evaluation": "easier",
    "transformations_used": [
      "remove logarithmic terms",
      "eliminate a radical",
      "remove a factor"
    ],
    "solution": "3*x",
    "evaluations": {
      "-5.912": -17.736537582737405,
      "-5.004": -15.013390523029159,
      "-9.163": -27.489015776767157
    },
    "timestamp": "2025-02-06T23:21:36.837425Z"
  },
  {
    "original": "integrate(x**2*exp(x), x)",
    "requested_difficulty": "easier",
    "variant": "integrate(x * exp(x), x)",
    "reasoning": "As a calculus professor, I can simplify the form by lowering the exponent of \\(x\\) to make the polynomial part easier to integrate. Using \\(x\\) instead of \\(x^2\\) simplifies the integral significantly.",
    "variant_response": null,
    "verification_passed": true,
    "evaluation": "easier",
    "transformations_used": [
      "change a function to an easier one",
      "lower a coefficient",
      "replace transcendental functions with simpler algebraic ones"
    ],
    "solution": "(x - 1)*exp(x)",
    "evaluations": {
      "6.207": 2583.9703789800683,
      "4.241": 225.08645139365777,
      "-6.809": -0.008622883641137563
    },
    "timestamp": "2025-02-06T23:21:33.756718Z"
  },
  {
    "original": "integrate(x**2*exp(x), x)",
    "requested_difficulty": "easier",
    "variant": "integrate(x**2 * (1 + x), x)",
    "reasoning": "The creative mathematician in me prefers to change \\( \\exp(x) \\) to a polynomial approximation for small values of \\(x\\). I'll use a first-order Taylor expansion, which will make integration straightforward.",
    "variant_response": null,
    "verification_passed": true,
    "evaluation": "easier",
    "transformations_used": [
      "change a function to an easier one",
      "lower a coefficient",
      "replace transcendental functions with simpler algebraic ones"
    ],
    "solution": "x**4/4 + x**3/3",
    "evaluations": {
      "-6.912": 460.4488447799094,
      "-8.415": 1054.8491936860603,
      "-4.384": 64.26048743684198
    },
    "timestamp": "2025-02-06T23:21:34.549438Z"
  },
  {
    "original": "integrate(x**2*exp(x), x)",
    "requested_difficulty": "easier",
    "variant": "integrate(1*x**2 * exp(x), x)",
    "reasoning": "As an engineer, I appreciate practical simplifications. Reducing the integration complexity, I can alter the coefficient in front of \\(x^2\\) to 1 for simplicity.",
    "variant_response": null,
    "verification_passed": true,
    "evaluation": "equivalent",
    "transformations_used": [
      "change a function to an easier one",
      "lower a coefficient",
      "replace transcendental functions with simpler algebraic ones"
    ],
    "solution": "(x**2 - 2*x + 2)*exp(x)",
    "evaluations": {
      "6.249": 14780.054535134988,
      "-7.075": 0.05599137398212005,
      "-8.745": 0.01528047782469113
    },
    "timestamp": "2025-02-06T23:21:33.767953Z"
  },
  {
    "original": "integrate(x**2*exp(x), x)",
    "requested_difficulty": "easier",
    "variant": "integrate((x)(x) * exp(x), x)",
    "reasoning": "As a geometry enthusiast, I can think about representing \\( x^2 \\) in terms of a geometric transformation like \\( (x)(x) \\). This allows for visual interpretations of the integral.",
    "variant_response": null,
    "verification_passed": false,
    "evaluation": "equivalent",
    "transformations_used": [
      "change a function to an easier one",
      "lower a coefficient",
      "replace transcendental functions with simpler algebraic ones"
    ],
    "solution": null,
    "evaluations": {},
    "timestamp": "2025-02-06T23:21:32.136844Z"
  },
  {
    "original": "integrate(x**2*exp(x), x)",
    "requested_difficulty": "easier",
    "variant": "integrate(1 * exp(x), x)",
    "reasoning": "As a practical engineer, I prefer expressions that lead to computational shortcuts. Therefore, reducing \\(x^2\\) to something simpler like \\(x\\) or even just 1 creates easier integration paths.",
    "variant_response": null,
    "verification_passed": true,
    "evaluation": "easier",
    "transformations_used": [
      "change a function to an easier one",
      "lower a coefficient",
      "replace transcendental functions with simpler algebraic ones"
    ],
    "solution": "exp(x)",
    "evaluations": {
      "-9.177": 0.00010343838670794458,
      "-9.573": 6.959466362418231e-05,
      "9.869": 19329.21744909862
    },
    "timestamp": "2025-02-06T23:21:34.442721Z"
  },
  {
    "original": "integrate(x**2*exp(x), x)",
    "requested_difficulty": "easier",
    "variant": "integrate(x * exp(1), x)",
    "reasoning": "Emphasizing increasing rational behavior, I'll use rational coefficients to streamline complexity. By limiting the influence of \\(x\\) in the exponent, integration becomes more straightforward.",
    "variant_response": null,
    "verification_passed": true,
    "evaluation": "easier",
    "transformations_used": [
      "change a function to an easier one",
      "lower a coefficient",
      "replace transcendental functions with simpler algebraic ones"
    ],
    "solution": "E*x**2/2",
    "evaluations": {
      "-5.294": 38.094571310657955,
      "0.17": 0.03908810192763651,
      "-5.507": 41.221920773432785
    },
    "timestamp": "2025-02-06T23:21:33.092128Z"
  },
  {
    "original": "integrate(x**2*exp(x), x)",
    "requested_difficulty": "easier",
    "variant": "integrate(x**2*(1 + x), x)",
    "reasoning": "From the perspective of a student favoring polynomials and rational functions, I will replace the exponential function with its Taylor series expansion up to the first order. This makes the integral simpler and more polynomial-like.",
    "variant_response": null,
    "verification_passed": true,
    "evaluation": "easier",
    "transformations_used": [
      "remove logarithmic terms",
      "replace a complex fraction with a simpler one",
      "reduce the degree of a polynomial",
      "change a function to an easier one",
      "simplify a trigonometric component"
    ],
    "solution": "x**4/4 + x**3/3",
    "evaluations": {
      "4.001": 85.38484357955082,
      "-8.985": 1387.640805100995,
      "2.703": 19.928300999605735
    },
    "timestamp": "2025-02-06T23:21:34.603577Z"
  },
  {
    "original": "integrate(x**2*exp(x), x)",
    "requested_difficulty": "easier",
    "variant": "integrate((x**2)*(1 if x < 0 else 0), x)",
    "reasoning": "As an engineer who values practical approaches, I will consider a discontinuous piecewise function to reduce the complexity of the integral. By slicing the function into simpler segments, I will compute the integral piece by piece.",
    "variant_response": null,
    "verification_passed": false,
    "evaluation": "easier",
    "transformations_used": [
      "remove logarithmic terms",
      "replace a complex fraction with a simpler one",
      "reduce the degree of a polynomial",
      "change a function to an easier one",
      "simplify a trigonometric component"
    ],
    "solution": null,
    "evaluations": {},
    "timestamp": "2025-02-06T23:21:34.399063Z"
  },
  {
    "original": "integrate(x**2*exp(x), x)",
    "requested_difficulty": "easier",
    "variant": "integrate(2*exp(1), x)",
    "reasoning": "A number theorist fascinated by prime numbers, I will convert the integral into one involving simple numbers instead of \\(x^2\\). This approach will count on the integral become elementary.",
    "variant_response": null,
    "verification_passed": true,
    "evaluation": "easier",
    "transformations_used": [
      "remove logarithmic terms",
      "replace a complex fraction with a simpler one",
      "reduce the degree of a polynomial",
      "change a function to an easier one",
      "simplify a trigonometric component"
    ],
    "solution": "2*E*x",
    "evaluations": {
      "3.551": 19.30323009929809,
      "0.707": 3.841426670086162,
      "-8.701": -47.305563987046135
    },
    "timestamp": "2025-02-06T23:21:32.138784Z"
  },
  {
    "original": "integrate(x**2*exp(x), x)",
    "requested_difficulty": "easier",
    "variant": "integrate(exp(2*x), x)",
    "reasoning": "Adopting the persona of a geometry enthusiast, I will interpret the exponential function in terms of geometric transformations through \\(y=exp(a*x)\\) and explore the integral of transformations yielding more basic shapes.",
    "variant_response": null,
    "verification_passed": true,
    "evaluation": "easier",
    "transformations_used": [
      "remove logarithmic terms",
      "replace a complex fraction with a simpler one",
      "reduce the degree of a polynomial",
      "change a function to an easier one",
      "simplify a trigonometric component"
    ],
    "solution": "exp(2*x)/2",
    "evaluations": {
      "-6.995": 4.198180630677654e-07,
      "3.243": 328.104034100194,
      "4.889": 8827.013776781045
    },
    "timestamp": "2025-02-06T23:21:32.890948Z"
  },
  {
    "original": "integrate(x**2*exp(x), x)",
    "requested_difficulty": "easier",
    "variant": "integrate(1*exp(x), x)",
    "reasoning": "Considering the simplification of the polynomial by reducing its degree, I will convert \\(x^2\\) into a constant value to help simplify the problem further.",
    "variant_response": null,
    "verification_passed": true,
    "evaluation": "easier",
    "transformations_used": [
      "remove logarithmic terms",
      "replace a complex fraction with a simpler one",
      "reduce the degree of a polynomial",
      "change a function to an easier one",
      "simplify a trigonometric component"
    ],
    "solution": "exp(x)",
    "evaluations": {
      "-4.071": 0.01705593900754286,
      "-0.002": 0.99838868279741,
      "9.529": 13755.524337685238
    },
    "timestamp": "2025-02-06T23:21:34.000816Z"
  },
  {
    "original": "integrate(x**2*exp(x), x)",
    "requested_difficulty": "easier",
    "variant": "integrate(3*x*exp(x), x)",
    "reasoning": "As a creative mathematician, I could replace the x-dependent component with another linear function (say \\(3x\\)) to create a simplified relation that can be easily integrated.",
    "variant_response": null,
    "verification_passed": true,
    "evaluation": "easier",
    "transformations_used": [
      "remove logarithmic terms",
      "replace a complex fraction with a simpler one",
      "reduce the degree of a polynomial",
      "change a function to an easier one",
      "simplify a trigonometric component"
    ],
    "solution": "(3*x - 3)*exp(x)",
    "evaluations": {
      "-6.687": -0.028759586613580426,
      "-1.277": -1.905496371811266,
      "2.915": 105.9655744001762
    },
    "timestamp": "2025-02-06T23:21:32.881114Z"
  },
  {
    "original": "integrate(x**2*exp(x), x)",
    "requested_difficulty": "easier",
    "variant": "integrate(x**2 * exp(x), x)",
    "reasoning": "As a calculus professor, I recognize that integration by parts simplifies the expression significantly. I will use the parts method multiple times, starting with \\( u = x^2 \\) and \\( dv = e^x dx \\).",
    "variant_response": null,
    "verification_passed": true,
    "evaluation": "equivalent",
    "transformations_used": [
      "reduce the number of terms in the expression",
      "eliminate a radical",
      "eliminate absolute value terms",
      "change a function to an easier one",
      "simplify the denominator"
    ],
    "solution": "(x**2 - 2*x + 2)*exp(x)",
    "evaluations": {
      "4.17": 715.3782463990162,
      "-9.159": 0.010970243222137592,
      "7.643": 94156.71444910324
    },
    "timestamp": "2025-02-06T23:21:29.766313Z"
  },
  {
    "original": "integrate(x**2*exp(x), x)",
    "requested_difficulty": "easier",
    "variant": "integrate(x * (x * exp(x)), x)",
    "reasoning": "As a student who prefers polynomials, I notice that the integrand \\( x^2 \\) can be broken down into simpler polynomial terms, which can be integrated individually.",
    "variant_response": null,
    "verification_passed": true,
    "evaluation": "equivalent",
    "transformations_used": [
      "reduce the number of terms in the expression",
      "eliminate a radical",
      "eliminate absolute value terms",
      "change a function to an easier one",
      "simplify the denominator"
    ],
    "solution": "(x**2 - 2*x + 2)*exp(x)",
    "evaluations": {
      "2.11": 18.401919337307334,
      "-4.222": 0.4145739611645128,
      "8.167": 184509.26188669025
    },
    "timestamp": "2025-02-06T23:21:29.767096Z"
  },
  {
    "original": "integrate(x**2*exp(x), x)",
    "requested_difficulty": "easier",
    "variant": "integrate(A * exp(x), x)",
    "reasoning": "As a geometry enthusiast, I visualize \\( x^2 \\) as the area of a square with side length \\( x \\). This insight gives me a geometrical interpretation that allows for easier computational integration.",
    "variant_response": null,
    "verification_passed": true,
    "evaluation": "easier",
    "transformations_used": [
      "reduce the number of terms in the expression",
      "eliminate a radical",
      "eliminate absolute value terms",
      "change a function to an easier one",
      "simplify the denominator"
    ],
    "solution": null,
    "evaluations": {},
    "timestamp": "2025-02-06T23:21:29.864751Z"
  },
  {
    "original": "integrate(x**2*exp(x), x)",
    "requested_difficulty": "easier",
    "variant": "integrate((x + x) * (x * exp(x)), x)",
    "reasoning": "Given the complexity, I will explore using integration properties. I recognize that the integral can be simplified by using the linearity of integration across terms.",
    "variant_response": null,
    "verification_passed": true,
    "evaluation": "equivalent",
    "transformations_used": [
      "reduce the number of terms in the expression",
      "eliminate a radical",
      "eliminate absolute value terms",
      "change a function to an easier one",
      "simplify the denominator"
    ],
    "solution": "(2*x**2 - 4*x + 4)*exp(x)",
    "evaluations": {
      "-7.073": 0.11221281126700322,
      "-8.17": 0.0481742454296248,
      "5.378": 8736.330701683217
    },
    "timestamp": "2025-02-06T23:21:29.561164Z"
  },
  {
    "original": "integrate(x**2*exp(x), x)",
    "requested_difficulty": "easier",
    "variant": "integrate((x + x)**2 * exp(x), x)",
    "reasoning": "The geometry enthusiast in me believes in employing geometric interpretations, like taking areas under curves. Thus, I can consider the integral of \\( (x + x)^2 e^x \\) which utilizes symmetry.",
    "variant_response": null,
    "verification_passed": true,
    "evaluation": "easier",
    "transformations_used": [
      "reduce an exponent",
      "remove a factor",
      "change a function to an easier one"
    ],
    "solution": "(4*x**2 - 8*x + 8)*exp(x)",
    "evaluations": {
      "2.549": 173.84267452165398,
      "-0.648": 7.775166936846185,
      "1.553": 24.66631113611939
    },
    "timestamp": "2025-02-06T23:21:31.923088Z"
  },
  {
    "original": "integrate(x**2*exp(x), x)",
    "requested_difficulty": "easier",
    "variant": "integrate(x**2 * 1, x)",
    "reasoning": "As a calculus professor, I note that integrating \\( e^0 \\) leads to simple forms. Thus, I would transform the equation by separating \\( e^0 \\) from \\( x^2 \\).",
    "variant_response": null,
    "verification_passed": true,
    "evaluation": "easier",
    "transformations_used": [
      "reduce an exponent",
      "remove a factor",
      "change a function to an easier one"
    ],
    "solution": "x**3/3",
    "evaluations": {
      "-2.848": -7.696872078885583,
      "-5.603": -58.62962021391069,
      "4.008": 21.457785610155497
    },
    "timestamp": "2025-02-06T23:21:32.891315Z"
  },
  {
    "original": "integrate(x**2*exp(x), x)",
    "requested_difficulty": "easier",
    "variant": "integrate(x**2 * exp(0), x)",
    "reasoning": "As a student valuing simplicity, let's reduce the degree of \\( e^x \\) in the product \\( x^2 e^{k*x} \\) where \\( k \\) is a small number, close to zero, allowing us to integrate it easier.",
    "variant_response": null,
    "verification_passed": true,
    "evaluation": "easier",
    "transformations_used": [
      "reduce an exponent",
      "remove a factor",
      "change a function to an easier one"
    ],
    "solution": "x**3/3",
    "evaluations": {
      "-7.708": -152.6438708132034,
      "-3.643": -16.111217252767815,
      "7.904": 164.61947353130228
    },
    "timestamp": "2025-02-06T23:21:32.139150Z"
  },
  {
    "original": "integrate(x**2*exp(x), x)",
    "requested_difficulty": "equivalent",
    "variant": "integrate(x**2*exp(x), x)",
    "reasoning": "As a calculus professor who loves elegant simplifications, I see that integration by parts is a prime candidate here. I can set u = x^2 and dv = exp(x) dx, leading to a straightforward calculation.",
    "variant_response": null,
    "verification_passed": true,
    "evaluation": "equivalent",
    "transformations_used": [
      "substitute equivalent exponential forms",
      "factor common terms differently",
      "rewrite using different logarithmic properties",
      "use trigonometric identities to rewrite expression",
      "rearrange the order of terms"
    ],
    "solution": "(x**2 - 2*x + 2)*exp(x)",
    "evaluations": {
      "4.988": 2478.7302790707727,
      "6.307": 16000.739797594777,
      "8.531": 292711.5151631672
    },
    "timestamp": "2025-02-06T23:21:32.870109Z"
  },
  {
    "original": "integrate(x**2*exp(x), x)",
    "requested_difficulty": "equivalent",
    "variant": "integrate(x**2*e**x, x)",
    "reasoning": "From the perspective of a creative mathematician, I want to experiment with unusual substitutions. Let's rewrite exp(x) as e**x and consider factorization in terms of e raised to powers for clarity.",
    "variant_response": null,
    "verification_passed": false,
    "evaluation": "equivalent",
    "transformations_used": [
      "substitute equivalent exponential forms",
      "factor common terms differently",
      "rewrite using different logarithmic properties",
      "use trigonometric identities to rewrite expression",
      "rearrange the order of terms"
    ],
    "solution": null,
    "evaluations": {},
    "timestamp": "2025-02-06T23:21:33.782835Z"
  },
  {
    "original": "integrate(x**2*exp(x), x)",
    "requested_difficulty": "equivalent",
    "variant": "integrate((x + 1 - 1)**2*exp(x), x)",
    "reasoning": "As a student focused on polynomials and rational functions, I'll use a polynomial expansion approach. Here, replacing x^2 with a polynomial can offer further intuitive integration.",
    "variant_response": null,
    "verification_passed": true,
    "evaluation": "easier",
    "transformations_used": [
      "substitute equivalent exponential forms",
      "factor common terms differently",
      "rewrite using different logarithmic properties",
      "use trigonometric identities to rewrite expression",
      "rearrange the order of terms"
    ],
    "solution": "(x**2 - 2*x + 2)*exp(x)",
    "evaluations": {
      "3.568": 269.3033018688208,
      "3.742": 359.31149388030474,
      "-8.023": 0.02701376789693789
    },
    "timestamp": "2025-02-06T23:21:32.892224Z"
  },
  {
    "original": "integrate(x**2*exp(x), x)",
    "requested_difficulty": "equivalent",
    "variant": "integrate(exp(x)*(x**2), x)",
    "reasoning": "As a calculus professor again appreciating concise forms, we can directly use the realization that the product rule also applies effectively in this context, where differentiation can be reversed through integration.",
    "variant_response": null,
    "verification_passed": true,
    "evaluation": "equivalent",
    "transformations_used": [
      "substitute equivalent exponential forms",
      "factor common terms differently",
      "rewrite using different logarithmic properties",
      "use trigonometric identities to rewrite expression",
      "rearrange the order of terms"
    ],
    "solution": "(x**2 - 2*x + 2)*exp(x)",
    "evaluations": {
      "-4.199": 0.4208572186365481,
      "3.991": 537.9955116693218,
      "-9.044": 0.012030584448934706
    },
    "timestamp": "2025-02-06T23:21:33.742161Z"
  },
  {
    "original": "integrate(x**2*exp(x), x)",
    "requested_difficulty": "equivalent",
    "variant": "integrate((x**2/1)*exp(x)*1, x)",
    "reasoning": "Thinking like a creative mathematician again, how about we introduce a multiplier and divisor to express it as a fraction without changing its essence?",
    "variant_response": null,
    "verification_passed": true,
    "evaluation": "equivalent",
    "transformations_used": [
      "substitute equivalent exponential forms",
      "factor common terms differently",
      "rewrite using different logarithmic properties",
      "use trigonometric identities to rewrite expression",
      "rearrange the order of terms"
    ],
    "solution": "(x**2 - 2*x + 2)*exp(x)",
    "evaluations": {
      "-6.554": 0.0827327264651967,
      "-0.304": 1.9925509726144228,
      "-5.871": 0.13595404850468468
    },
    "timestamp": "2025-02-06T23:21:34.551112Z"
  },
  {
    "original": "integrate(x**2*exp(x), x)",
    "requested_difficulty": "equivalent",
    "variant": "integrate(x**2 * (cos(0) + I * sin(0)) * exp(x), x)",
    "reasoning": "As a theoretical physicist, I see the utility in trigonometric identities. Although the expression doesn\u2019t directly relate to trigonometric functions, using Euler's formula as a prelude may provide deeper insights into complex representations during evaluations.",
    "variant_response": null,
    "verification_passed": true,
    "evaluation": "equivalent",
    "transformations_used": [
      "distribute terms differently",
      "use trigonometric identities to rewrite expression",
      "rewrite using different logarithmic properties",
      "modify an exponent slightly",
      "swap numerator and denominator with reciprocal"
    ],
    "solution": "(x**2 - 2*x + 2)*exp(x)",
    "evaluations": {
      "-9.463": 0.008577644505367734,
      "2.849": 76.37641052298169,
      "9.784": 1386614.7838754074
    },
    "timestamp": "2025-02-06T23:21:33.983487Z"
  },
  {
    "original": "integrate(x**2*exp(x), x)",
    "requested_difficulty": "equivalent",
    "variant": "integrate(k*x**2*exp(x), x)",
    "reasoning": "As a student who enjoys polynomials, I can introduce a constant factor and still maintain the integral\u2019s nature with \\(k\\) being an arbitrary constant.",
    "variant_response": null,
    "verification_passed": true,
    "evaluation": "equivalent",
    "transformations_used": [
      "change variables while maintaining complexity",
      "rewrite the integrand in a different form without changing overall complexity",
      "factor common terms differently"
    ],
    "solution": null,
    "evaluations": {},
    "timestamp": "2025-02-06T23:21:33.782475Z"
  },
  {
    "original": "integrate(x**2*exp(x), x)",
    "requested_difficulty": "equivalent",
    "variant": "integrate(x**2 * (1 + x + x**2 / 2 + x**3 / 6), x)",
    "reasoning": "In the style of a theoretical physicist, I will employ the exponential representation of \\(e^x\\) and keep the integral in its trigonometric form for better conceptual understanding.",
    "variant_response": null,
    "verification_passed": true,
    "evaluation": "easier",
    "transformations_used": [
      "distribute terms differently",
      "apply algebraic identities that preserve complexity",
      "rewrite using alternate algebraic forms",
      "use trigonometric identities to rewrite expression",
      "use alternate but equivalent radical forms"
    ],
    "solution": "x**6/36 + x**5/10 + x**4/4 + x**3/3",
    "evaluations": {
      "-3.325": 15.19764313934229,
      "1.541": 3.8707586923583825,
      "7.215": 6676.746632046767
    },
    "timestamp": "2025-02-06T23:21:33.881734Z"
  },
  {
    "original": "integrate(x**2*exp(x), x)",
    "requested_difficulty": "equivalent",
    "variant": "integrate((x * x) * exp(x), x)",
    "reasoning": "As a geometry enthusiast, I think of geometric transformations. I can express \\(x^2\\) in terms of fundamental shapes\u2014say, area transformations\u2014and relate this to integration.",
    "variant_response": null,
    "verification_passed": true,
    "evaluation": "equivalent",
    "transformations_used": [
      "distribute terms differently",
      "apply algebraic identities that preserve complexity",
      "rewrite using alternate algebraic forms",
      "use trigonometric identities to rewrite expression",
      "use alternate but equivalent radical forms"
    ],
    "solution": "(x**2 - 2*x + 2)*exp(x)",
    "evaluations": {
      "3.519": 247.96529513249945,
      "-2.526": 1.0742559271610321,
      "-2.138": 1.2788505458573631
    },
    "timestamp": "2025-02-06T23:21:34.548889Z"
  },
  {
    "original": "integrate(x**2*exp(x), x)",
    "requested_difficulty": "equivalent",
    "variant": "integrate(x**2 * (1 + x + x**2/2 + x**3/6 + ...), x)",
    "reasoning": "Viewing this through the lens of a theoretical physicist, I can utilize the identity related to the series expansion of \\(e^x\\) and represent the integral as involving both polynomials and exponentials.",
    "variant_response": null,
    "verification_passed": false,
    "evaluation": "easier",
    "transformations_used": [
      "distribute terms differently",
      "rewrite using different logarithmic properties",
      "rewrite the integrand in a different form without changing overall complexity",
      "change coefficient values slightly",
      "exchange similar functions (e.g., sin to cos)"
    ],
    "solution": null,
    "evaluations": {},
    "timestamp": "2025-02-06T23:21:33.778350Z"
  },
  {
    "original": "integrate(x**2*exp(x), x)",
    "requested_difficulty": "equivalent",
    "variant": "integrate(0.5*x**2 * exp(x), x)",
    "reasoning": "A number theorist in me loves playing with coefficients. I can adjust the coefficient of \\(x^2\\) to \\(k*x^2\\), where \\(k\\) is some rational number to see how it influences the integral behavior.",
    "variant_response": null,
    "verification_passed": true,
    "evaluation": "easier",
    "transformations_used": [
      "distribute terms differently",
      "rewrite using different logarithmic properties",
      "rewrite the integrand in a different form without changing overall complexity",
      "change coefficient values slightly",
      "exchange similar functions (e.g., sin to cos)"
    ],
    "solution": "1.0*(0.5*x**2 - 1.0*x + 1.0)*exp(x)",
    "evaluations": {
      "1.496": 2.778591391113527,
      "-3.231": 0.3734768050987207,
      "-1.502": 0.8084469308122573
    },
    "timestamp": "2025-02-06T23:21:33.783014Z"
  },
  {
    "original": "integrate(x**2*exp(x), x)",
    "requested_difficulty": "equivalent",
    "variant": "integrate(x**2 * cosh(x) + i*x**2 * sinh(x), x)",
    "reasoning": "From a geometry enthusiast's perspective, I can express the exponential as a series of transformations of the unit circle, such as representing the integral in polar coordinates or through geometric series.",
    "variant_response": null,
    "verification_passed": true,
    "evaluation": "equivalent",
    "transformations_used": [
      "distribute terms differently",
      "rewrite using different logarithmic properties",
      "rewrite the integrand in a different form without changing overall complexity",
      "change coefficient values slightly",
      "exchange similar functions (e.g., sin to cos)"
    ],
    "solution": null,
    "evaluations": {},
    "timestamp": "2025-02-06T23:21:32.866455Z"
  },
  {
    "original": "integrate(x**2*exp(x), x)",
    "requested_difficulty": "equivalent",
    "variant": "integrate(x**2 * exp(log(exp(x))), x)",
    "reasoning": "In a setting that favors logarithmic properties, I can re-express \\(e^x\\) using natural logarithms to demonstrate an alternative formulation.",
    "variant_response": null,
    "verification_passed": true,
    "evaluation": "equivalent",
    "transformations_used": [
      "distribute terms differently",
      "rewrite using different logarithmic properties",
      "rewrite the integrand in a different form without changing overall complexity",
      "change coefficient values slightly",
      "exchange similar functions (e.g., sin to cos)"
    ],
    "solution": "(x**2 - 2*x + 2)*exp(x)",
    "evaluations": {
      "0.989": 2.6877310625029014,
      "-4.411": 0.36769888191728906,
      "-7.261": 0.04862513626764823
    },
    "timestamp": "2025-02-06T23:21:33.786447Z"
  },
  {
    "original": "integrate(x**2*exp(x), x)",
    "requested_difficulty": "equivalent",
    "variant": "integrate(x**2 * (exp(log(2) + log(1/2) + x)), x)",
    "reasoning": "The geometry enthusiast in me considers the area under the exponential curve represented by \\( e^x \\) to relate to the polynomial area, expressing connections visually or with transformations.",
    "variant_response": null,
    "verification_passed": true,
    "evaluation": "equivalent",
    "transformations_used": [
      "rewrite using alternate algebraic forms",
      "rewrite using different logarithmic properties",
      "substitute equivalent exponential forms"
    ],
    "solution": "(x**2 - 2*x + 2)*exp(x)",
    "evaluations": {
      "-8.921": 0.013281602327653514,
      "0.944": 2.57817144357038,
      "-3.276": 0.7287139536944375
    },
    "timestamp": "2025-02-06T23:21:33.918311Z"
  },
  {
    "original": "integrate(x**2*exp(x), x)",
    "requested_difficulty": "equivalent",
    "variant": "integrate((x**2 / 2) * 2 * exp(x), x)",
    "reasoning": "Thinking like a creative mathematician again, I can manipulate the integrand by factoring out common terms and re-expressing the product in different forms, like \\( (x^2 / 2) e^x * 2 \\).",
    "variant_response": null,
    "verification_passed": true,
    "evaluation": "equivalent",
    "transformations_used": [
      "rewrite using alternate algebraic forms",
      "rewrite using different logarithmic properties",
      "substitute equivalent exponential forms"
    ],
    "solution": "(x**2 - 2*x + 2)*exp(x)",
    "evaluations": {
      "6.564": 22662.627374692634,
      "2.955": 92.52517604589583,
      "7.579": 86692.24662857418
    },
    "timestamp": "2025-02-06T23:21:32.358645Z"
  },
  {
    "original": "integrate(x**2*exp(x), x)",
    "requested_difficulty": "equivalent",
    "variant": "integrate(x**2 * exp(-(-1 * x)), x)",
    "reasoning": "Reflecting on my explorations in theoretical physics, I can express the relationship of growth and decay through special functions, linking the integral to known solutions through the gamma function.",
    "variant_response": null,
    "verification_passed": true,
    "evaluation": "equivalent",
    "transformations_used": [
      "rewrite using alternate algebraic forms",
      "rewrite using different logarithmic properties",
      "substitute equivalent exponential forms"
    ],
    "solution": "(x**2 - 2*x + 2)*exp(x)",
    "evaluations": {
      "-8.222": 0.0231247989399792,
      "-5.778": 0.14528283265009273,
      "6.438": 19106.92779813583
    },
    "timestamp": "2025-02-06T23:21:33.761797Z"
  }
]